{
  "step_id": 16,
  "has_goal_ee_xyz": true,
  "goal_ee_xyz": [
    0.550000011920929,
    0.0,
    0.20000000298023224
  ],
  "goal_error_final_m": 0.09309413284063339,
  "has_scene_flows": true,
  "has_scene_visibility": true,
  "has_scene_depth_valid_mask": true,
  "has_task_n_obs": true,
  "has_task_n_infl": true,
  "has_runtime_policy": true,
  "scene_flows_shape": [
    11,
    4096,
    3
  ],
  "scene_visibility_shape": [
    11,
    4096
  ],
  "scene_depth_valid_mask_shape": [
    11,
    4096
  ],
  "task_n_obs": 1990,
  "task_n_infl": 2750,
  "task_selector_reason": "",
  "runtime_policy": {
    "seed_robot_mask_enabled": true,
    "gripper_pose_enabled": true,
    "task_use_visibility": true,
    "task_use_depth_valid": true,
    "task_ablation_mode": "obs_infl",
    "cooldown_active": false
  },
  "pw_cost_debug": {
    "enabled": true,
    "reason": "ok",
    "ms": 2877.8038043528795,
    "eval_ranges": [
      {
        "device": "cuda:0",
        "start": 0,
        "end": 128,
        "samples": 128
      },
      {
        "device": "cuda:1",
        "start": 128,
        "end": 256,
        "samples": 128
      }
    ],
    "timing": {
      "mode": "multi",
      "devices": [
        "cuda:0",
        "cuda:1"
      ],
      "replicas": [
        {
          "device": "cuda:0",
          "B": 128,
          "chunk_size": 32,
          "chunks": 4,
          "t_scene_to_torch_ms": 0.6650499999523163,
          "t_scene_features_ms": 6.833252497017384,
          "t_dist2robot_ms": 6.196215748786926,
          "t_model_ms": 2747.3075157031417,
          "t_reduce_ms": 4.255435429513454,
          "t_total_ms": 2764.8165682330728,
          "dist2robot_mode": "t0_repeat",
          "t_prepare_batch_ms": 68.61979141831398,
          "t_total_with_prepare_ms": 2833.4363596513867,
          "start": 0,
          "end": 128,
          "samples": 128
        },
        {
          "device": "cuda:1",
          "B": 128,
          "chunk_size": 32,
          "chunks": 4,
          "t_scene_to_torch_ms": 0.5119442939758301,
          "t_scene_features_ms": 6.816346198320389,
          "t_dist2robot_ms": 6.162956357002258,
          "t_model_ms": 2779.6902963891625,
          "t_reduce_ms": 4.696547985076904,
          "t_total_ms": 2797.1563283354044,
          "dist2robot_mode": "t0_repeat",
          "t_prepare_batch_ms": 75.43187402188778,
          "t_total_with_prepare_ms": 2872.588202357292,
          "start": 128,
          "end": 256,
          "samples": 128
        }
      ]
    }
  },
  "timing_breakdown": {
    "request_id": "df8d4d1c-50bd-433c-9efe-18e094b1ea25",
    "step_id": 16,
    "t_decode_ms": 0.17770566046237946,
    "t_cameras_ms": 11.735559441149235,
    "t_pw_build_ms": 921.8839555978775,
    "pw_build_breakdown": {
      "t_window_push_ms": 0.024529173970222473,
      "t_scene_build_ms": 904.6168746426702,
      "scene_build_breakdown": {
        "ms_total": 904.4393924996257,
        "cams": {
          "back": {
            "ms_total": 859.5361094921827,
            "ms_frames": 0.014522112905979156,
            "ms_valid0": 0.0789053738117218,
            "ms_workspace0": 10.571836493909359,
            "ms_robot_mask0": 16.701416112482548,
            "ms_project_mask0": 6.88561424612999,
            "ms_rasterize_mask0": 4.344537854194641,
            "ms_morph_mask0": 5.385742522776127,
            "ms_query": 0.007877126336097717,
            "ms_sample_rgb0": 0.1924745738506317,
            "ms_track": 771.3730745017529,
            "ms_lift": 3.7622088566422462,
            "ms_lift3d": 1.8919426947832108,
            "ms_transform": 0.545998103916645,
            "ms_ws_filter": 0.7537044584751129,
            "ms_robot_filter": 0.0,
            "ms_ee_filter": 0.0,
            "ms_ok": 0.08961185812950134,
            "ms_pack": 0.354875810444355,
            "ms_stability": 0.17753057181835175,
            "ms_shift_valid": 0.06803125143051147,
            "ms_shift_workspace": 10.651467368006706,
            "ms_shift_robot_mask": 16.921442933380604,
            "ms_project_mask_shift": 7.1567269042134285,
            "ms_rasterize_mask_shift": 4.399292171001434,
            "ms_morph_mask_shift": 5.220470018684864,
            "shift_mask_cache_hit": 0,
            "shift_mask_cache_miss": 1,
            "ms_advance": 0.9594215080142021,
            "n_query": 2048,
            "hw": [
              180,
              320
            ]
          },
          "side": {
            "ms_total": 866.774688474834,
            "ms_frames": 0.014662742614746094,
            "ms_valid0": 0.0723889097571373,
            "ms_workspace0": 11.207861825823784,
            "ms_robot_mask0": 15.971268527209759,
            "ms_project_mask0": 6.415257230401039,
            "ms_rasterize_mask0": 4.603232257068157,
            "ms_morph_mask0": 4.8755258321762085,
            "ms_query": 0.005492940545082092,
            "ms_sample_rgb0": 0.1707412302494049,
            "ms_track": 771.3730745017529,
            "ms_lift": 5.960283800959587,
            "ms_lift3d": 2.779526636004448,
            "ms_transform": 0.9541250765323639,
            "ms_ws_filter": 1.2921998277306557,
            "ms_robot_filter": 0.0,
            "ms_ee_filter": 0.0,
            "ms_ok": 0.1341523602604866,
            "ms_pack": 0.6409259513020515,
            "ms_stability": 0.19352417439222336,
            "ms_shift_valid": 0.06692763417959213,
            "ms_shift_workspace": 11.240001767873764,
            "ms_shift_robot_mask": 15.93799702823162,
            "ms_project_mask_shift": 6.459572352468967,
            "ms_rasterize_mask_shift": 4.623483866453171,
            "ms_morph_mask_shift": 4.723489284515381,
            "shift_mask_cache_hit": 0,
            "shift_mask_cache_miss": 1,
            "ms_advance": 0.8571641519665718,
            "n_query": 2048,
            "hw": [
              180,
              320
            ]
          }
        }
      },
      "t_build_batch_ms": 0.02739671617746353,
      "t_gripper_pose_fk_ms": 15.93749038875103,
      "t_task_selector_ms": 1.0708458721637726
    },
    "pcd_points": 0,
    "t_pcd_ms": 0.0,
    "t_solver_ms": 2924.28729031235,
    "pw_ms": 2877.8038043528795
  }
}