{
  "step_id": 13,
  "has_goal_ee_xyz": true,
  "actions_finite": true,
  "joint_limit_penalty_mean": 0.0,
  "joint_limit_penalty_q95": 0.0,
  "goal_ee_xyz": [
    0.550000011920929,
    0.0,
    0.20000000298023224
  ],
  "goal_error_final_m": 0.10978065431118011,
  "has_scene_flows": true,
  "has_scene_visibility": true,
  "has_scene_depth_valid_mask": true,
  "has_task_n_obs": true,
  "has_task_n_infl": true,
  "has_runtime_policy": true,
  "scene_flows_shape": [
    11,
    4096,
    3
  ],
  "scene_visibility_shape": [
    11,
    4096
  ],
  "scene_depth_valid_mask_shape": [
    11,
    4096
  ],
  "task_n_obs": 1678,
  "task_n_infl": 2324,
  "task_selector_reason": "",
  "runtime_policy": {
    "seed_robot_mask_enabled": true,
    "gripper_pose_enabled": true,
    "task_use_visibility": true,
    "task_use_depth_valid": true,
    "task_ablation_mode": "obs_infl",
    "cooldown_active": false
  },
  "pw_cost_debug": {
    "enabled": true,
    "reason": "ok",
    "ms": 3089.2340866848826,
    "actions_finite": true,
    "joint_limit_penalty_mean": 0.0,
    "joint_limit_penalty_q95": 0.0,
    "eval_ranges": [
      {
        "device": "cuda:0",
        "start": 0,
        "end": 128,
        "samples": 128
      },
      {
        "device": "cuda:1",
        "start": 128,
        "end": 256,
        "samples": 128
      }
    ],
    "timing": {
      "mode": "multi",
      "devices": [
        "cuda:0",
        "cuda:1"
      ],
      "replicas": [
        {
          "device": "cuda:0",
          "B": 128,
          "chunk_size": 32,
          "chunks": 4,
          "t_scene_to_torch_ms": 0.47436635941267014,
          "t_scene_features_ms": 6.876031868159771,
          "t_dist2robot_ms": 6.194255314767361,
          "t_model_ms": 2992.579199373722,
          "t_reduce_ms": 4.432588815689087,
          "t_total_ms": 3009.88039188087,
          "dist2robot_mode": "t0_repeat",
          "t_prepare_batch_ms": 77.28172093629837,
          "t_total_with_prepare_ms": 3087.1621128171682,
          "start": 0,
          "end": 128,
          "samples": 128
        },
        {
          "device": "cuda:1",
          "B": 128,
          "chunk_size": 32,
          "chunks": 4,
          "t_scene_to_torch_ms": 0.6058886647224426,
          "t_scene_features_ms": 6.7562442272901535,
          "t_dist2robot_ms": 6.076637655496597,
          "t_model_ms": 2950.8571717888117,
          "t_reduce_ms": 4.054548218846321,
          "t_total_ms": 2967.715408653021,
          "dist2robot_mode": "t0_repeat",
          "t_prepare_batch_ms": 72.83706776797771,
          "t_total_with_prepare_ms": 3040.5524764209986,
          "start": 128,
          "end": 256,
          "samples": 128
        }
      ]
    }
  },
  "timing_breakdown": {
    "request_id": "1f7c802a-382b-404b-b2ca-d7b2da5c91ee",
    "step_id": 13,
    "t_decode_ms": 0.20206253975629807,
    "t_cameras_ms": 12.096012011170387,
    "t_pw_build_ms": 871.8829387798905,
    "pw_build_breakdown": {
      "t_window_push_ms": 0.024275854229927063,
      "t_scene_build_ms": 860.1422514766455,
      "scene_build_breakdown": {
        "ms_total": 860.0025149062276,
        "cams": {
          "back": {
            "ms_total": 828.6479627713561,
            "ms_frames": 0.013844110071659088,
            "ms_valid0": 0.08395407348871231,
            "ms_workspace0": 7.585084997117519,
            "ms_robot_mask0": 10.154138319194317,
            "ms_project_mask0": 4.6395109966397285,
            "ms_rasterize_mask0": 2.1847831085324287,
            "ms_morph_mask0": 3.2643163576722145,
            "ms_query": 0.0067176297307014465,
            "ms_sample_rgb0": 0.13215839862823486,
            "ms_track": 770.482525229454,
            "ms_lift": 3.8950396701693535,
            "ms_lift3d": 1.9692787900567055,
            "ms_transform": 0.5453294143080711,
            "ms_ws_filter": 0.7768776267766953,
            "ms_robot_filter": 0.0,
            "ms_ee_filter": 0.0,
            "ms_ok": 0.08450821042060852,
            "ms_pack": 0.39114151149988174,
            "ms_stability": 0.16164034605026245,
            "ms_shift_valid": 0.07175467908382416,
            "ms_shift_workspace": 7.803976535797119,
            "ms_shift_robot_mask": 10.227258317172527,
            "ms_project_mask_shift": 4.714061506092548,
            "ms_rasterize_mask_shift": 2.313366159796715,
            "ms_morph_mask_shift": 3.0787475407123566,
            "shift_mask_cache_hit": 0,
            "shift_mask_cache_miss": 1,
            "ms_advance": 0.6424020975828171,
            "n_query": 2048,
            "hw": [
              180,
              320
            ]
          },
          "side": {
            "ms_total": 831.8735528737307,
            "ms_frames": 0.011484138667583466,
            "ms_valid0": 0.06320048123598099,
            "ms_workspace0": 7.404974661767483,
            "ms_robot_mask0": 9.1285714879632,
            "ms_project_mask0": 3.9474647492170334,
            "ms_rasterize_mask0": 2.2541936486959457,
            "ms_morph_mask0": 2.8683487325906754,
            "ms_query": 0.005415640771389008,
            "ms_sample_rgb0": 0.15046540647745132,
            "ms_track": 770.482525229454,
            "ms_lift": 3.449494019150734,
            "ms_lift3d": 1.6889916732907295,
            "ms_transform": 0.4772953689098358,
            "ms_ws_filter": 0.7419874891638756,
            "ms_robot_filter": 0.0,
            "ms_ee_filter": 0.0,
            "ms_ok": 0.08076056838035583,
            "ms_pack": 0.35075657069683075,
            "ms_stability": 0.13834144920110703,
            "ms_shift_valid": 0.08066557347774506,
            "ms_shift_workspace": 7.4485233053565025,
            "ms_shift_robot_mask": 9.182310663163662,
            "ms_project_mask_shift": 3.9306357502937317,
            "ms_rasterize_mask_shift": 2.271096222102642,
            "ms_morph_mask_shift": 2.8838245198130608,
            "shift_mask_cache_hit": 0,
            "shift_mask_cache_miss": 1,
            "ms_advance": 0.5475394427776337,
            "n_query": 2048,
            "hw": [
              180,
              320
            ]
          }
        }
      },
      "t_build_batch_ms": 0.02225581556558609,
      "t_gripper_pose_fk_ms": 10.823872871696949,
      "t_task_selector_ms": 0.7063448429107666
    },
    "pcd_points": 0,
    "t_pcd_ms": 0.0,
    "t_solver_ms": 3131.766906939447,
    "pw_ms": 3089.2340866848826,
    "actions_finite": true,
    "joint_limit_penalty_mean": 0.0,
    "joint_limit_penalty_q95": 0.0
  }
}